foldx/__init__.py
foldx/foldx.py
foldx/foldxHandler.py
handlers/__init__.py
handlers/fileHandler.py
handlers/systemHandler.py
handlers/uniprot.py
handlers/urlRetrieveHandler.py
handlers/xmlToPy.py
notebooks/__init__.py
paramx/__init__.py
paramx/paramx.py
pyfoldx/foldx/__init__.py
pyfoldx/foldx/foldx.py
pyfoldx/foldx/foldxHandler.py
pyfoldx/handlers/__init__.py
pyfoldx/handlers/fileHandler.py
pyfoldx/handlers/systemHandler.py
pyfoldx/handlers/uniprot.py
pyfoldx/handlers/urlRetrieveHandler.py
pyfoldx/handlers/xmlToPy.py
pyfoldx/paramx/__init__.py
pyfoldx/paramx/paramx.py
pyfoldx/structure/__init__.py
pyfoldx/structure/atom.py
pyfoldx/structure/cifParser.py
pyfoldx/structure/ensemble.py
pyfoldx/structure/misc.py
pyfoldx/structure/pdbParser.py
pyfoldx/structure/residue.py
pyfoldx/structure/structure.py
scripts/__init__.py
scripts/computeMissense3dMutations.py
scripts/generateJSONFiles.py
scripts/parseMissense3dFrustration.py
scripts/parseMissense3dMutations.py
structure/__init__.py
structure/atom.py
structure/cifParser.py
structure/ensemble.py
structure/misc.py
structure/pdbParser.py
structure/residue.py
structure/structure.py
pyfoldx-0.1.1.dist-info/METADATA
pyfoldx-0.1.1.dist-info/WHEEL
pyfoldx-0.1.1.dist-info/top_level.txt
pyfoldx-0.1.1.dist-info/RECORD
